version_tools/__init__.py
version_tools/version.py
pyversioninc-0.0.13.dist-info/LICENSE
pyversioninc-0.0.13.dist-info/METADATA
pyversioninc-0.0.13.dist-info/WHEEL
pyversioninc-0.0.13.dist-info/top_level.txt
pyversioninc-0.0.13.dist-info/RECORD
