Metadata-Version: 2.1
Name: pyversioninc
Version: 0.0.13
Summary: Collection of classes and functions used for the versioning
Home-page: https://github.com/BriceFotzo/py_version_tools
Author: Brice Fotzo
Author-email: brice.fotzo@hotmail.com
License: UNKNOWN
Keywords: python packages,version,python versions,versioning
Platform: UNKNOWN
